setup.py
invoicing/__init__.py
invoicing/invoice.py
invoicing_2024_0.0.0.egg-info/PKG-INFO
invoicing_2024_0.0.0.egg-info/SOURCES.txt
invoicing_2024_0.0.0.egg-info/dependency_links.txt
invoicing_2024_0.0.0.egg-info/requires.txt
invoicing_2024_0.0.0.egg-info/top_level.txt